README.rst
setup.py
aiohttp_route_decorator/__init__.py
aiohttp_route_decorator.egg-info/PKG-INFO
aiohttp_route_decorator.egg-info/SOURCES.txt
aiohttp_route_decorator.egg-info/dependency_links.txt
aiohttp_route_decorator.egg-info/requires.txt
aiohttp_route_decorator.egg-info/top_level.txt
tests/__init__.py
tests/conftest.py
tests/test_route_collector.py