Metadata-Version: 1.0
Name: aiohttp_route_decorator
Version: 0.1.4
Summary: aiohttp @route decorator that doesn't need the app singleton
Home-page: https://github.com/IlyaSemenov/aiohttp_route_decorator
Author: Ilya Semenov
Author-email: ilya@semenov.co
License: BSD
Platform: UNKNOWN
